[
    {
        "url": "https://raw.githubusercontent.com/cosmix-extensions/testd/builds/XXXFreeProvider.csx",
        "status": 1,
        "version": 5,
        "name": "XXXFreeProvider",
        "internalName": "XXXFreeProvider",
        "authors": [
            "cosmix-extensions"
        ],
        "description": "XXXFree Movies and Videos",
        "fileSize": 48698,
        "repositoryUrl": "https://github.com/cosmix-extensions/testd",
        "language": "en",
        "tvTypes": [
            "Movie"
        ],
        "iconUrl": "https://t3.gstatic.com/faviconV2?client=SOCIAL&type=FAVICON&fallback_opts=TYPE,SIZE,URL&url=https://xxxfree.watch/&size=128",
        "apiVersion": 1,
        "fileHash": "sha256-2ee4c46b5d3f8921249f6960bc16084890a4c1b749e9c2924e5ca9a077cf6974",
        "jarFileSize": 109044,
        "jarUrl": "https://raw.githubusercontent.com/cosmix-extensions/testd/builds/XXXFreeProvider.jar",
        "jarHash": "sha256-6a179bc0e94a78e2fa91f9a26f5717ccc3136cbd313aa1ab13b99c9162d5105a"
    }
]